smartpathways/MapGenerator.py
smartpathways/__init__.py
smartpathways/pathwaygen.py
smartpathways-0.0.3.dist-info/METADATA
smartpathways-0.0.3.dist-info/WHEEL
smartpathways-0.0.3.dist-info/top_level.txt
smartpathways-0.0.3.dist-info/RECORD
