Metadata-Version: 2.1
Name: smartpathways
Version: 0.0.3
Summary: MathU Smart Pathways package
Author: Luca Lohrentz
Author-email: <luca@mathu.co.za>
Keywords: python,first package
Classifier: Development Status :: 3 - Alpha
Classifier: Intended Audience :: Education
Classifier: Programming Language :: Python :: 2
Classifier: Programming Language :: Python :: 3
Classifier: Operating System :: MacOS :: MacOS X
Classifier: Operating System :: Microsoft :: Windows
